sys_calc/__init__.py
sys_calc-0.0.1.dist-info/METADATA
sys_calc-0.0.1.dist-info/WHEEL
sys_calc-0.0.1.dist-info/top_level.txt
sys_calc-0.0.1.dist-info/RECORD
