Metadata-Version: 2.1
Name: sys_calc
Version: 0.0.1
Summary: This is the simplest module for quick work with float - bin,oct,hex.
Home-page: https://github.com/S4CBS/sys_calc
Author: S4CBS
Author-email: aap200789@gmail.com
Project-URL: GitHub, https://github.com/S4CBS/sys_calc
Keywords: sys_calc
Classifier: Programming Language :: Python :: 3.11
Classifier: License :: OSI Approved :: MIT License
Classifier: Operating System :: OS Independent
Requires-Python: >=3.6
